eqsor/__init__.py
eqsor/cli.py
eqsor/eqsor_binded.cpython-312-x86_64-linux-gnu.so
eqsor-1.0.6.dist-info/METADATA
eqsor-1.0.6.dist-info/WHEEL
eqsor-1.0.6.dist-info/entry_points.txt
eqsor-1.0.6.dist-info/top_level.txt
eqsor-1.0.6.dist-info/RECORD
